CHANGELOG.md
pyramid_hybridauth/__init__.py
pyramid_hybridauth/config.py
pyramid_hybridauth/exceptions.py
pyramid_hybridauth/provider.py
pyramid_hybridauth/services/__init__.py
pyramid_hybridauth/services/facebook.py
pyramid_hybridauth/services/google.py
pyramid_hybridauth/services/ninja.py
pyramid_hybridauth/services/twitter.py
pyramid_hybridauth/services/yahoo.py
pyramid_hybridauth-1.1.1.dist-info/METADATA
pyramid_hybridauth-1.1.1.dist-info/WHEEL
pyramid_hybridauth-1.1.1.dist-info/RECORD
